{
  "BottomMenu": {
    "description": "Auto imported from components/BottomMenu.vue"
  },
  "Mindmap": {
    "description": "Auto imported from components/Mindmap.vue"
  },
  "Calendars": {
    "description": "Auto imported from components/calendars/Calendars.vue"
  },
  "Notifications": {
    "description": "Auto imported from components/notifications/Notifications.vue"
  },
  "MessagesForm": {
    "description": "Auto imported from components/messages/MessagesForm.vue"
  },
  "ContentsFormNewContent": {
    "description": "Auto imported from components/contents/contentsFormNewContent.vue"
  },
  "PostsEdit": {
    "description": "Auto imported from components/posts/PostsEdit.vue"
  },
  "PostsFormSelect": {
    "description": "Auto imported from components/posts/PostsFormSelect.vue"
  },
  "PostsFormTagList": {
    "description": "Auto imported from components/posts/PostsFormTagList.vue"
  },
  "PostsFormTitle": {
    "description": "Auto imported from components/posts/PostsFormTitle.vue"
  },
  "PostsModal": {
    "description": "Auto imported from components/posts/PostsModal.vue"
  },
  "RoomsRoomEditForm": {
    "description": "Auto imported from components/rooms/RoomEditForm.vue"
  },
  "RoomsCard": {
    "description": "Auto imported from components/rooms/RoomsCard.vue"
  },
  "RoomsDetailForm": {
    "description": "Auto imported from components/rooms/RoomsDetailForm.vue"
  },
  "RoomsFormDeadlineDate": {
    "description": "Auto imported from components/rooms/RoomsFormDeadlineDate.vue"
  },
  "RoomsFormDeadlineTime": {
    "description": "Auto imported from components/rooms/RoomsFormDeadlineTime.vue"
  },
  "RoomsFormTitle": {
    "description": "Auto imported from components/rooms/RoomsFormTitle.vue"
  },
  "UserFormEmail": {
    "description": "Auto imported from components/user/userFormEmail.vue"
  },
  "UserFormPassword": {
    "description": "Auto imported from components/user/userFormPassword.vue"
  },
  "UsersCard": {
    "description": "Auto imported from components/users/UsersCard.vue"
  }
}
